app_min.py
nano_csv2json-0.1.0.dist-info/licenses/LICENSE
nano_csv2json-0.1.0.dist-info/METADATA
nano_csv2json-0.1.0.dist-info/WHEEL
nano_csv2json-0.1.0.dist-info/entry_points.txt
nano_csv2json-0.1.0.dist-info/top_level.txt
nano_csv2json-0.1.0.dist-info/RECORD
