Metadata-Version: 2.4
Name: nano-csv2json
Version: 0.1.0
Summary: Tiny CSV → JSON Lines converter in ~1KB (zero deps)
Author: ozgunlu
License: MIT
Project-URL: Homepage, https://github.com/ozgunlu/nano-csv2json
Project-URL: Issues, https://github.com/ozgunlu/nano-csv2json/issues
Requires-Python: >=3.8
License-File: LICENSE
Dynamic: license-file
